{"annotationInfo":{},"version":2,"attachments":{},"docInfo":{"progress":0,"pagemarkType":"SINGLE_COLUMN","properties":{},"archived":false,"flagged":false,"tags":{"depression":{"id":"depression","label":"depression"},"/personal/health":{"id":"/personal/health","label":"/personal/health"}},"attachments":{},"nrPages":1,"fingerprint":"1NUYSd4ZL1GXusN4Y2d9","added":"2019-12-11T05:55:28.991Z","filename":"12AEcoUqxD-Depression___Robert_Sapolsky_Rocks.phz","uuid":"z2019-12-11T05:55:50.294Z+000156-572445699453","title":"Depression - Robert Sapolsky Rocks","url":"https://www.robertsapolskyrocks.com/depression.html","lastUpdated":"2019-12-11T05:55:50.294Z","nrComments":0,"nrNotes":0,"nrFlashcards":0,"nrTextHighlights":0,"nrAreaHighlights":0,"nrAnnotations":0},"pageMetas":{"1":{"pagemarks":{},"notes":{},"comments":{},"questions":{},"flashcards":{},"textHighlights":{},"areaHighlights":{},"screenshots":{},"thumbnails":{},"readingProgress":{},"pageInfo":{"num":1,"dimensions":{"width":1024,"height":5554}}}}}