{"annotationInfo":{},"version":2,"attachments":{},"docInfo":{"progress":0,"pagemarkType":"SINGLE_COLUMN","properties":{},"archived":false,"flagged":false,"tags":{"/management":{"id":"/management","label":"/management"},"/READ_LATER":{"id":"/READ_LATER","label":"/READ_LATER"},"management":{"id":"management","label":"management"},"project_management":{"id":"project_management","label":"project_management"}},"attachments":{},"nrPages":1,"fingerprint":"12Y1dQmuz9u2k5EVURmW","added":"2019-12-10T09:43:42.455Z","filename":"1GY2GmknA3-Software_Isn_t_the_Problem___Gadgetopia.phz","uuid":"z2019-12-10T09:44:09.588Z+000038-572445699453","title":"Software Isn’t the Problem – Gadgetopia","url":"https://gadgetopia.com/post/13333","lastUpdated":"2019-12-10T09:44:09.588Z","nrComments":0,"nrNotes":0,"nrFlashcards":0,"nrTextHighlights":0,"nrAreaHighlights":0,"nrAnnotations":0},"pageMetas":{"1":{"pagemarks":{},"notes":{},"comments":{},"questions":{},"flashcards":{},"textHighlights":{},"areaHighlights":{},"screenshots":{},"thumbnails":{},"readingProgress":{},"pageInfo":{"num":1,"dimensions":{"width":750,"height":12181}}}}}